streaming_form_data-2.0.0.dist-info/RECORD
streaming_form_data-2.0.0.dist-info/WHEEL
streaming_form_data-2.0.0.dist-info/top_level.txt
streaming_form_data-2.0.0.dist-info/METADATA
streaming_form_data-2.0.0.dist-info/licenses/LICENSE.txt
streaming_form_data/targets.py
streaming_form_data/validators.py
streaming_form_data/__init__.py
streaming_form_data/parser.py
streaming_form_data/_parser.c
streaming_form_data/_parser.cpython-313-darwin.so
