Metadata-Version: 2.4
Name: streaming-form-data
Version: 2.0.0
Summary: Streaming parser for multipart/form-data
Author-email: Siddhant Goel <me@sgoel.dev>
Project-URL: Homepage, https://github.com/siddhantgoel/streaming-form-data
Project-URL: Repository, https://github.com/siddhantgoel/streaming-form-data
Project-URL: Documentation, https://streaming-form-data.readthedocs.io
Keywords: cython,form-data,forms,http,multipart,streaming,web
Classifier: Development Status :: 4 - Beta
Classifier: Environment :: Web Environment
Classifier: Intended Audience :: Developers
Classifier: License :: OSI Approved :: MIT License
Classifier: Topic :: Internet :: WWW/HTTP
Classifier: Topic :: Internet :: WWW/HTTP :: Browsers
Classifier: Topic :: Internet :: WWW/HTTP :: Dynamic Content
Classifier: Topic :: Internet :: WWW/HTTP :: HTTP Servers
Classifier: Programming Language :: Cython
Classifier: Programming Language :: Python :: 3
Classifier: Programming Language :: Python :: 3.10
Classifier: Programming Language :: Python :: 3.11
Classifier: Programming Language :: Python :: 3.12
Classifier: Programming Language :: Python :: 3.13
Classifier: Programming Language :: Python :: 3 :: Only
Requires-Python: >=3.10
License-File: LICENSE.txt
Requires-Dist: smart-open>=7.0.5
Requires-Dist: aiofiles>=23.2.1
Dynamic: license-file
